{
    "metadata": {
        "source": "../experiments/outputs/human/pilot/CreativeStoryGeneration_20240910_1533.csv",
        "num_questions": 4,
        "participant_id": "R_8mxVCke66o4WOVl",
        "model": "human"
    },
    "data": [
        {
            "id": "petrol-diesel-pump",
            "items": [
                "petrol",
                "diesel",
                "pump"
            ],
            "pos": [
                "noun",
                "noun",
                "verb"
            ],
            "semantic_distance": "low",
            "boring_theme": "going to the petrol station to pump diesel into a vehicle",
            "output": "The pump for my bicycle broke the other day. It got a puncture. Would you be able to believe the irony, because I certainly wouldn't! This meant that until I could source a new one, or fix that one, I was borrowing and driving my mum's car. The only problem with this, was that the first time I took it to get filled up I was not sure whether it took petrol or diesel...",
            "result_id": "R_8mxVCke66o4WOVl_Q1"
        },
        {
            "id": "stamp-letter-send",
            "items": [
                "stamp",
                "letter",
                "send"
            ],
            "pos": [
                "noun",
                "noun",
                "verb"
            ],
            "semantic_distance": "low",
            "boring_theme": "putting a stamp on the envelop containing a letter to send it",
            "output": "There are some letters that I have always wanted to send, but I never have. Whether that's because I don't quite have the words, or I have the words but not the recipient. One time, it was because I didn't have a stamp, and then the letter got so destroyed just sitting in my bag that I thought fate was telling me to give up. Maybe today is the day.",
            "result_id": "R_8mxVCke66o4WOVl_Q2"
        },
        {
            "id": "organ-empire-comply",
            "items": [
                "organ",
                "empire",
                "comply"
            ],
            "pos": [
                "noun",
                "noun",
                "verb"
            ],
            "semantic_distance": "high",
            "boring_theme": "having an organ empire and complying with regulations",
            "output": "There is a belief that the most beautiful instrument is the organ, which you might find gracing a church and whose music might sound melodic to your ears. To me, this instrument makes me think of centuries of kings and queens who forced people to comply. The empire that they built based on the expectation that the people needed them. So I prefer the lute.",
            "result_id": "R_8mxVCke66o4WOVl_Q3"
        },
        {
            "id": "gloom-payment-exist",
            "items": [
                "gloom",
                "payment",
                "exist"
            ],
            "pos": [
                "noun",
                "noun",
                "verb"
            ],
            "semantic_distance": "high",
            "boring_theme": "the feeling of gloom you have about an existing payment",
            "output": "She didn't want to exist anymore. She had made the final payment on her mortgage, and now owned the house she had been living in for forty years - but all she felt was gloom. In every ten year plan she made, she allowed herself some breathing space - she would finally achieve her dreams once she had paid that final sum. She couldn't bring herself to do anything now that she was there.",
            "result_id": "R_8mxVCke66o4WOVl_Q4"
        }
    ]
}