{
    "metadata": {
        "source": "../experiments/outputs/human/pilot/CreativeStoryGeneration_20240910_1533.csv",
        "num_questions": 4,
        "participant_id": "R_8VyQYwyI8iMwwKJ",
        "model": "human"
    },
    "data": [
        {
            "id": "petrol-diesel-pump",
            "items": [
                "petrol",
                "diesel",
                "pump"
            ],
            "semantic_distance": "low",
            "output": "It was still another 10 miles to the next petrol or diesel pump. I didn't even know what this old battered car took but whatever it was it was running on fumes. I'd soon know about it if it was diesel as i think i heard once that you cant let a diesel tank run drive or the engine would go kaput. Every extra mile the car got was one fewer to the safety and one more away them.",
            "result_id": "R_8VyQYwyI8iMwwKJ_Q1"
        },
        {
            "id": "stamp-letter-send",
            "items": [
                "stamp",
                "letter",
                "send"
            ],
            "semantic_distance": "low",
            "output": "I picked up the initial stamp, carved with an ornate letter 'P' and pressed it into the hot wax that sealed the intensely personal letter firmly closed, safe from prying eyes. It maybe seemed like an old fashioned, outdated way to send a message but who knows where emails or whatsapps end up these day. A wax sealed letter, delivered by Uber  was the modern day messenger courier   ",
            "result_id": "R_8VyQYwyI8iMwwKJ_Q2"
        },
        {
            "id": "organ-empire-comply",
            "items": [
                "organ",
                "empire",
                "comply"
            ],
            "semantic_distance": "high",
            "output": "The vast church organ in the nave of the church seem like the vestige of an long forgotten empire. Endless vertical pipes that seemed to have been built by a larger race, not looking like they would comply with any current laws of physics. The sound was otherworldly to match",
            "result_id": "R_8VyQYwyI8iMwwKJ_Q3"
        },
        {
            "id": "gloom-payment-exist",
            "items": [
                "gloom",
                "payment",
                "exist"
            ],
            "semantic_distance": "high",
            "output": "The gloom of the overhanging clouds passed over the house plunging it into darkness and blotting out the surrounding world. Did it even exist anymore. All that could been seen through the gloom was the rain sheeting down, acting as a long awaited payment to the earth after years of drought. ",
            "result_id": "R_8VyQYwyI8iMwwKJ_Q4"
        }
    ]
}